gotmgui/__init__.py
gotmgui/__main__.py
gotmgui/batch.py
gotmgui/commonqt.py
gotmgui/gotmgui.ico
gotmgui/gotmgui.py
gotmgui/icon.png
gotmgui/logo.png
gotmgui/scenariobuilder.py
gotmgui/setup.py
gotmgui/simulator.py
gotmgui/visualizer.py
gotmgui/core/__init__.py
gotmgui/core/common.py
gotmgui/core/namelist.py
gotmgui/core/report.py
gotmgui/core/result.py
gotmgui/core/scenario.py
gotmgui/core/settings.py
gotmgui/core/simulator.py
gotmgui/icons/advanced.png
gotmgui/icons/back.png
gotmgui/icons/gohome.png
gotmgui/icons/next.png
gotmgui/icons/readme.txt
gotmgui/reporttemplates/default/index.xml
gotmgui/reporttemplates/default/main.css
gotmgui/reporttemplates/default/main.js
gotmgui/schemas/report/gotmgui.schema
gotmgui/schemas/result/gotmgui.schema
gotmgui/schemas/scenario/gotm-5.0_gotmgui-0.5.0.converter
gotmgui/schemas/scenario/gotm-5.2_gotmgui-0.5.0.converter
gotmgui/schemas/scenario/gotm-5.3_gotmgui-0.5.0.converter
gotmgui/schemas/scenario/gotmgui-0.5.0.schema
gotmgui/schemas/settings/gotmgui.schema
gotmgui/util/__init__.py
gotmgui/util/extractncdata.py
gotmgui/util/mergeobs.py
gotmgui/util/nml2xml.py
gotmgui/util/xml2nml.py
gotmgui-0.1.2.dist-info/METADATA
gotmgui-0.1.2.dist-info/WHEEL
gotmgui-0.1.2.dist-info/entry_points.txt
gotmgui-0.1.2.dist-info/top_level.txt
gotmgui-0.1.2.dist-info/RECORD
