Metadata-Version: 2.1
Name: gotmgui
Version: 0.1.2
Summary: --- update - 
Home-page: http://github.com/BoldingBruggeman/gotmgui
Author: Jorn Bruggeman
Author-email: jorn@bolding-bruggeman.com
License: GPL
Platform: UNKNOWN
Classifier: Development Status :: 4 - Beta
Classifier: Intended Audience :: Science/Research
Classifier: Topic :: Scientific/Engineering
Classifier: License :: OSI Approved :: GNU General Public License (GPL)
Classifier: Programming Language :: Python
Requires-Dist: xmlplot (>=0.9.19)
